uuid_blake3-0.2.0.dist-info/METADATA
uuid_blake3-0.2.0.dist-info/WHEEL
uuid_blake3-0.2.0.dist-info/licenses/LICENSE
uuid_blake3/__init__.py
uuid_blake3/uuid_blake3.pyd
uuid_blake3-0.2.0.dist-info/RECORD
